amiami/__init__.py
amiami/amiami.py
amiami-0.0.2.dist-info/LICENSE
amiami-0.0.2.dist-info/METADATA
amiami-0.0.2.dist-info/WHEEL
amiami-0.0.2.dist-info/top_level.txt
amiami-0.0.2.dist-info/RECORD
