Metadata-Version: 2.1
Name: amiami
Version: 0.0.2
Summary: amiami lame api scraper that works through the api
Home-page: https://bitbucket.org/marvinody/amiami/
Author: marvinody
Author-email: manny@sadpanda.moe
License: UNKNOWN
Platform: UNKNOWN
Classifier: Programming Language :: Python :: 3.5
Requires-Dist: certifi (==2019.3.9)
Requires-Dist: chardet (==3.0.4)
Requires-Dist: idna (==2.8)
Requires-Dist: requests (==2.21.0)
Requires-Dist: urllib3 (==1.24.1)
